pyidi/__init__.py
pyidi/fiducial.py
pyidi/load_analysis copy.py
pyidi/load_analysis.py
pyidi/progress_bar.py
pyidi/pyidi.py
pyidi/pyidi_legacy.py
pyidi/tools.py
pyidi/video_reader.py
pyidi/GUIs/__init__.py
pyidi/GUIs/gui.py
pyidi/GUIs/result_viewer.py
pyidi/GUIs/selection.py
pyidi/GUIs/subset_selection.py
pyidi/methods/__init__.py
pyidi/methods/_directional_lucas_kanade.py
pyidi/methods/_gradient_based_optical_flow.py
pyidi/methods/_lucas_kanade.py
pyidi/methods/_lucas_kanade_scipy.py
pyidi/methods/_lucas_kanade_scipy2.py
pyidi/methods/_simplified_optical_flow.py
pyidi/methods/idi_method.py
pyidi/postprocessing/__init__.py
pyidi/postprocessing/_motion_magnification.py
pyidi-1.3.1.dist-info/METADATA
pyidi-1.3.1.dist-info/WHEEL
pyidi-1.3.1.dist-info/licenses/LICENSE
pyidi-1.3.1.dist-info/RECORD
