Metadata-Version: 2.4
Name: pyidi
Version: 1.3.1
Summary: Python Image Displacement Identification.
Project-URL: homepage, https://github.com/ladisk/pyidi
Project-URL: documentation, https://pyidi.readthedocs.io/en/latest/
Project-URL: source, https://github.com/ladisk/pyidi
Author-email: "Klemen Zaletelj, Domen Gorjup, Janko Slavič et al." <janko.slavic@fs.uni-lj.si>
Maintainer-email: "Klemen Zaletelj, Domen Gorjup, Janko Slavič et al." <janko.slavic@fs.uni-lj.si>
License-Expression: MIT
License-File: LICENSE
Keywords: computer vision,dic,displacement identification,gradient-based
Classifier: Development Status :: 5 - Production/Stable
Classifier: Intended Audience :: Developers
Classifier: License :: OSI Approved :: MIT License
Classifier: Programming Language :: Python :: 3.10
Classifier: Topic :: Scientific/Engineering
Requires-Python: >=3.10
Requires-Dist: atpbar
Requires-Dist: imageio[pyav]
Requires-Dist: magicgui
Requires-Dist: mantichora==0.9.7
Requires-Dist: matplotlib>=3.0.0
Requires-Dist: napari[all]
Requires-Dist: numba
Requires-Dist: numpy>=1.15.4
Requires-Dist: opencv-python
Requires-Dist: psutil
Requires-Dist: pymraw>=0.30
Requires-Dist: scipy>=1.0.0
Requires-Dist: tqdm
Provides-Extra: dev
Requires-Dist: build; extra == 'dev'
Requires-Dist: nbsphinx; extra == 'dev'
Requires-Dist: nbsphinx-link; extra == 'dev'
Requires-Dist: pytest; extra == 'dev'
Requires-Dist: sphinx; extra == 'dev'
Requires-Dist: sphinx-book-theme; extra == 'dev'
Requires-Dist: sphinx-copybutton; extra == 'dev'
Requires-Dist: twine; extra == 'dev'
Provides-Extra: qt
Requires-Dist: pyqt6; extra == 'qt'
Requires-Dist: pyqtgraph; extra == 'qt'
